LICENSE
MANIFEST.in
README.md
README.rst
setup.py
mhcnames/__init__.py
mhcnames/allele_name.py
mhcnames/allele_parse_error.py
mhcnames/class2.py
mhcnames/mouse.py
mhcnames/normalization.py
mhcnames/parsing_helpers.py
mhcnames/species.py
mhcnames.egg-info/PKG-INFO
mhcnames.egg-info/SOURCES.txt
mhcnames.egg-info/dependency_links.txt
mhcnames.egg-info/requires.txt
mhcnames.egg-info/top_level.txt
test/test_bad_inputs.py
test/test_dog.py
test/test_human_class1.py
test/test_human_class2.py
test/test_macaque.py
test/test_mouse_class1.py
test/test_mouse_class2.py
test/test_rat_alleles.py
test/test_sheep.py
test/test_swine.py